{
  "created_utc": "2026-07-17T05:24:22.665363+00:00",
  "package": "ai.liquid.lfmdemo",
  "pid": 30577,
  "sampling_interval_s": 0.2,
  "active_sample_count": 5,
  "request": {
    "label": "memory_attribution",
    "mode": "asr",
    "audio": "asr.wav",
    "run_index": 1,
    "measured": true,
    "first_text_ms": 889.8839997127652,
    "first_audio_ms": null,
    "total_ms": 1654.2827496305108,
    "transcript": "The stale smell of old beer lingers. It takes heat to bring out the odor. A cold dip restores health and zest. A salt pickle tastes fine with ham. Tacos al pastor are my favorite. A zestful food is the hot cross bun.",
    "reference": "The stale smell of old beer lingers. It takes heat to bring out the odor. A cold dip restores health and zest. A salt pickle tastes fine with ham. Tacos al pastor are my favorite. A zestful food is the hot cross bun.",
    "wer_percent": 0.0,
    "exact_normalized": true,
    "audio_output_bytes_f32": 0,
    "audio_output_sample_rate": null,
    "audio_output_seconds": null,
    "sse_events": 58
  },
  "captures": {
    "idle": {
      "captured_utc": "2026-07-17T05:24:19.587532+00:00",
      "pid": 30577,
      "summary": {
        "status": {
          "Name": "liblfmserver.so",
          "Umask": "0077",
          "State": "S (sleeping)",
          "Tgid": "30577",
          "Ngid": "0",
          "Pid": "30577",
          "PPid": "30487",
          "TracerPid": "0",
          "Uid": "10538\t10538\t10538\t10538",
          "Gid": "10538\t10538\t10538\t10538",
          "FDSize": "256",
          "Groups": "3003 9997 20538 50538 99909997",
          "Kthread": "0",
          "VmPeak": 13911840,
          "VmSize": 13911840,
          "VmLck": 0,
          "VmPin": 0,
          "VmHWM": 1730468,
          "VmRSS": 1730468,
          "RssAnon": 1006440,
          "RssFile": 723728,
          "RssShmem": 300,
          "VmData": 2050700,
          "VmStk": 136,
          "VmExe": 1220,
          "VmLib": 9744,
          "VmPTE": 3764,
          "VmSwap": 0,
          "CoreDumping": "0",
          "THP_enabled": "1",
          "untag_mask": "0xffffffffffffff",
          "Threads": "17",
          "SigQ": "0/57649",
          "SigPnd": "0000000000000000",
          "ShdPnd": "0000000000000000",
          "SigBlk": "0000000080001204",
          "SigIgn": "0000002000001001",
          "SigCgt": "0000004c400084fa",
          "CapInh": "0000000000000000",
          "CapPrm": "0000000000000000",
          "CapEff": "0000000000000000",
          "CapBnd": "0000000000000000",
          "CapAmb": "0000000000000000",
          "NoNewPrivs": "0",
          "Seccomp": "2",
          "Seccomp_filters": "1",
          "Speculation_Store_Bypass": "thread vulnerable",
          "SpeculationIndirectBranch": "unknown",
          "Cpus_allowed": "ff",
          "Cpus_allowed_list": "0-7",
          "Mems_allowed": "1",
          "Mems_allowed_list": "0",
          "voluntary_ctxt_switches": "22",
          "nonvoluntary_ctxt_switches": "163"
        },
        "smaps_totals_kib": {
          "Anonymous": 1006972,
          "Rss": 1731244,
          "Private_Clean": 721316,
          "Shared_Clean": 2628,
          "Referenced": 1731192,
          "Swap": 0,
          "Private_Dirty": 1006972,
          "Size": 13911840,
          "Pss": 1728302,
          "Shared_Dirty": 328,
          "SwapPss": 0,
          "AnonHugePages": 387072
        },
        "category_totals_kib": {
          "anonymous": {
            "Anonymous": 1006632,
            "Rss": 1006632,
            "Private_Clean": 0,
            "Shared_Clean": 0,
            "Referenced": 1006632,
            "Swap": 0,
            "Private_Dirty": 1006632,
            "Size": 13183344,
            "Pss": 1006632,
            "Shared_Dirty": 0,
            "SwapPss": 0,
            "AnonHugePages": 387072
          },
          "gguf_weights": {
            "Anonymous": 0,
            "Rss": 714380,
            "Private_Clean": 714380,
            "Shared_Clean": 0,
            "Referenced": 714380,
            "Swap": 0,
            "Private_Dirty": 0,
            "Size": 714380,
            "Pss": 714380,
            "Shared_Dirty": 0,
            "SwapPss": 0,
            "AnonHugePages": 0
          },
          "shared_libraries": {
            "Anonymous": 296,
            "Rss": 8984,
            "Private_Clean": 6936,
            "Shared_Clean": 1752,
            "Referenced": 8932,
            "Swap": 0,
            "Private_Dirty": 296,
            "Size": 11000,
            "Pss": 7239,
            "Shared_Dirty": 0,
            "SwapPss": 0,
            "AnonHugePages": 0
          },
          "other_file_backed": {
            "Anonymous": 44,
            "Rss": 916,
            "Private_Clean": 0,
            "Shared_Clean": 872,
            "Referenced": 916,
            "Swap": 0,
            "Private_Dirty": 44,
            "Size": 1492,
            "Pss": 51,
            "Shared_Dirty": 0,
            "SwapPss": 0,
            "AnonHugePages": 0
          },
          "device_mappings": {
            "Anonymous": 0,
            "Rss": 328,
            "Private_Clean": 0,
            "Shared_Clean": 0,
            "Referenced": 328,
            "Swap": 0,
            "Private_Dirty": 0,
            "Size": 1560,
            "Pss": 0,
            "Shared_Dirty": 328,
            "SwapPss": 0,
            "AnonHugePages": 0
          },
          "special_mappings": {
            "Anonymous": 0,
            "Rss": 4,
            "Private_Clean": 0,
            "Shared_Clean": 4,
            "Referenced": 4,
            "Swap": 0,
            "Private_Dirty": 0,
            "Size": 64,
            "Pss": 0,
            "Shared_Dirty": 0,
            "SwapPss": 0,
            "AnonHugePages": 0
          }
        },
        "rows": [
          {
            "category": "anonymous",
            "detail": "[anon:scudo:secondary]",
            "mapping_count": 77,
            "Anonymous": 982004,
            "Rss": 982004,
            "Private_Clean": 0,
            "Shared_Clean": 0,
            "Referenced": 982004,
            "Swap": 0,
            "Private_Dirty": 982004,
            "Size": 2002236,
            "Pss": 982004,
            "Shared_Dirty": 0,
            "SwapPss": 0,
            "AnonHugePages": 387072
          },
          {
            "category": "gguf_weights",
            "detail": "LFM2.5-Audio-1.5B-Q4_0.gguf",
            "mapping_count": 2,
            "Anonymous": 0,
            "Rss": 667908,
            "Private_Clean": 667908,
            "Shared_Clean": 0,
            "Referenced": 667908,
            "Swap": 0,
            "Private_Dirty": 0,
            "Size": 667908,
            "Pss": 667908,
            "Shared_Dirty": 0,
            "SwapPss": 0,
            "AnonHugePages": 0
          },
          {
            "category": "gguf_weights",
            "detail": "tokenizer-LFM2.5-Audio-1.5B-Q4_0.gguf",
            "mapping_count": 2,
            "Anonymous": 0,
            "Rss": 46472,
            "Private_Clean": 46472,
            "Shared_Clean": 0,
            "Referenced": 46472,
            "Swap": 0,
            "Private_Dirty": 0,
            "Size": 46472,
            "Pss": 46472,
            "Shared_Dirty": 0,
            "SwapPss": 0,
            "AnonHugePages": 0
          },
          {
            "category": "anonymous",
            "detail": "[anon:scudo:primary]",
            "mapping_count": 33,
            "Anonymous": 23384,
            "Rss": 23384,
            "Private_Clean": 0,
            "Shared_Clean": 0,
            "Referenced": 23384,
            "Swap": 0,
            "Private_Dirty": 23384,
            "Size": 29952,
            "Pss": 23384,
            "Shared_Dirty": 0,
            "SwapPss": 0,
            "AnonHugePages": 0
          },
          {
            "category": "shared_libraries",
            "detail": "libliquid-audio.so",
            "mapping_count": 3,
            "Anonymous": 48,
            "Rss": 1852,
            "Private_Clean": 1804,
            "Shared_Clean": 0,
            "Referenced": 1852,
            "Swap": 0,
            "Private_Dirty": 48,
            "Size": 2428,
            "Pss": 1852,
            "Shared_Dirty": 0,
            "SwapPss": 0,
            "AnonHugePages": 0
          },
          {
            "category": "shared_libraries",
            "detail": "libllama.so",
            "mapping_count": 3,
            "Anonymous": 48,
            "Rss": 1760,
            "Private_Clean": 1712,
            "Shared_Clean": 0,
            "Referenced": 1760,
            "Swap": 0,
            "Private_Dirty": 48,
            "Size": 2080,
            "Pss": 1760,
            "Shared_Dirty": 0,
            "SwapPss": 0,
            "AnonHugePages": 0
          },
          {
            "category": "shared_libraries",
            "detail": "liblfmserver.so",
            "mapping_count": 3,
            "Anonymous": 28,
            "Rss": 1056,
            "Private_Clean": 1028,
            "Shared_Clean": 0,
            "Referenced": 1056,
            "Swap": 0,
            "Private_Dirty": 28,
            "Size": 1248,
            "Pss": 1056,
            "Shared_Dirty": 0,
            "SwapPss": 0,
            "AnonHugePages": 0
          },
          {
            "category": "other_file_backed",
            "detail": "/apex/com.android.runtime/bin/linker64",
            "mapping_count": 4,
            "Anonymous": 44,
            "Rss": 916,
            "Private_Clean": 0,
            "Shared_Clean": 872,
            "Referenced": 916,
            "Swap": 0,
            "Private_Dirty": 44,
            "Size": 1492,
            "Pss": 51,
            "Shared_Dirty": 0,
            "SwapPss": 0,
            "AnonHugePages": 0
          },
          {
            "category": "shared_libraries",
            "detail": "libggml-base.so",
            "mapping_count": 3,
            "Anonymous": 36,
            "Rss": 868,
            "Private_Clean": 832,
            "Shared_Clean": 0,
            "Referenced": 868,
            "Swap": 0,
            "Private_Dirty": 36,
            "Size": 932,
            "Pss": 868,
            "Shared_Dirty": 0,
            "SwapPss": 0,
            "AnonHugePages": 0
          },
          {
            "category": "shared_libraries",
            "detail": "libc++.so",
            "mapping_count": 4,
            "Anonymous": 36,
            "Rss": 820,
            "Private_Clean": 0,
            "Shared_Clean": 784,
            "Referenced": 768,
            "Swap": 0,
            "Private_Dirty": 36,
            "Size": 1028,
            "Pss": 39,
            "Shared_Dirty": 0,
            "SwapPss": 0,
            "AnonHugePages": 0
          },
          {
            "category": "shared_libraries",
            "detail": "libc.so",
            "mapping_count": 4,
            "Anonymous": 20,
            "Rss": 784,
            "Private_Clean": 0,
            "Shared_Clean": 764,
            "Referenced": 784,
            "Swap": 0,
            "Private_Dirty": 20,
            "Size": 960,
            "Pss": 21,
            "Shared_Dirty": 0,
            "SwapPss": 0,
            "AnonHugePages": 0
          },
          {
            "category": "anonymous",
            "detail": "[anon:.bss]",
            "mapping_count": 16,
            "Anonymous": 712,
            "Rss": 712,
            "Private_Clean": 0,
            "Shared_Clean": 0,
            "Referenced": 712,
            "Swap": 0,
            "Private_Dirty": 712,
            "Size": 944,
            "Pss": 712,
            "Shared_Dirty": 0,
            "SwapPss": 0,
            "AnonHugePages": 0
          },
          {
            "category": "shared_libraries",
            "detail": "libggml.so",
            "mapping_count": 3,
            "Anonymous": 28,
            "Rss": 660,
            "Private_Clean": 632,
            "Shared_Clean": 0,
            "Referenced": 660,
            "Swap": 0,
            "Private_Dirty": 28,
            "Size": 660,
            "Pss": 660,
            "Shared_Dirty": 0,
            "SwapPss": 0,
            "AnonHugePages": 0
          },
          {
            "category": "shared_libraries",
            "detail": "libggml-cpu-android_armv8.6_1.so",
            "mapping_count": 3,
            "Anonymous": 16,
            "Rss": 532,
            "Private_Clean": 516,
            "Shared_Clean": 0,
            "Referenced": 532,
            "Swap": 0,
            "Private_Dirty": 16,
            "Size": 700,
            "Pss": 532,
            "Shared_Dirty": 0,
            "SwapPss": 0,
            "AnonHugePages": 0
          },
          {
            "category": "shared_libraries",
            "detail": "libmtmd.so",
            "mapping_count": 3,
            "Anonymous": 16,
            "Rss": 428,
            "Private_Clean": 412,
            "Shared_Clean": 0,
            "Referenced": 428,
            "Swap": 0,
            "Private_Dirty": 16,
            "Size": 684,
            "Pss": 428,
            "Shared_Dirty": 0,
            "SwapPss": 0,
            "AnonHugePages": 0
          },
          {
            "category": "device_mappings",
            "detail": "/dev/__properties__/property_info",
            "mapping_count": 2,
            "Anonymous": 0,
            "Rss": 268,
            "Private_Clean": 0,
            "Shared_Clean": 0,
            "Referenced": 268,
            "Swap": 0,
            "Private_Dirty": 0,
            "Size": 280,
            "Pss": 0,
            "Shared_Dirty": 268,
            "SwapPss": 0,
            "AnonHugePages": 0
          },
          {
            "category": "shared_libraries",
            "detail": "libm.so",
            "mapping_count": 4,
            "Anonymous": 8,
            "Rss": 172,
            "Private_Clean": 0,
            "Shared_Clean": 164,
            "Referenced": 172,
            "Swap": 0,
            "Private_Dirty": 8,
            "Size": 228,
            "Pss": 11,
            "Shared_Dirty": 0,
            "SwapPss": 0,
            "AnonHugePages": 0
          },
          {
            "category": "anonymous",
            "detail": "[anon:bionic_alloc_small_objects]",
            "mapping_count": 14,
            "Anonymous": 116,
            "Rss": 116,
            "Private_Clean": 0,
            "Shared_Clean": 0,
            "Referenced": 116,
            "Swap": 0,
            "Private_Dirty": 116,
            "Size": 116,
            "Pss": 116,
            "Shared_Dirty": 0,
            "SwapPss": 0,
            "AnonHugePages": 0
          },
          {
            "category": "anonymous",
            "detail": "[stack]",
            "mapping_count": 1,
            "Anonymous": 92,
            "Rss": 92,
            "Private_Clean": 0,
            "Shared_Clean": 0,
            "Referenced": 92,
            "Swap": 0,
            "Private_Dirty": 92,
            "Size": 136,
            "Pss": 92,
            "Shared_Dirty": 0,
            "SwapPss": 0,
            "AnonHugePages": 0
          },
          {
            "category": "anonymous",
            "detail": "[anon:System property context nodes]",
            "mapping_count": 2,
            "Anonymous": 48,
            "Rss": 48,
            "Private_Clean": 0,
            "Shared_Clean": 0,
            "Referenced": 48,
            "Swap": 0,
            "Private_Dirty": 48,
            "Size": 48,
            "Pss": 48,
            "Shared_Dirty": 0,
            "SwapPss": 0,
            "AnonHugePages": 0
          },
          {
            "category": "shared_libraries",
            "detail": "libnetd_client.so",
            "mapping_count": 4,
            "Anonymous": 8,
            "Rss": 40,
            "Private_Clean": 0,
            "Shared_Clean": 32,
            "Referenced": 40,
            "Swap": 0,
            "Private_Dirty": 8,
            "Size": 40,
            "Pss": 8,
            "Shared_Dirty": 0,
            "SwapPss": 0,
            "AnonHugePages": 0
          },
          {
            "category": "anonymous",
            "detail": "[anon:linker_alloc]",
            "mapping_count": 4,
            "Anonymous": 28,
            "Rss": 28,
            "Private_Clean": 0,
            "Shared_Clean": 0,
            "Referenced": 28,
            "Swap": 0,
            "Private_Dirty": 28,
            "Size": 1920,
            "Pss": 28,
            "Shared_Dirty": 0,
            "SwapPss": 0,
            "AnonHugePages": 0
          },
          {
            "category": "anonymous",
            "detail": "[anon:stack_and_tls:30637]",
            "mapping_count": 1,
            "Anonymous": 20,
            "Rss": 20,
            "Private_Clean": 0,
            "Shared_Clean": 0,
            "Referenced": 20,
            "Swap": 0,
            "Private_Dirty": 20,
            "Size": 1008,
            "Pss": 20,
            "Shared_Dirty": 0,
            "SwapPss": 0,
            "AnonHugePages": 0
          },
          {
            "category": "anonymous",
            "detail": "[anon:cfi shadow]",
            "mapping_count": 10,
            "Anonymous": 20,
            "Rss": 20,
            "Private_Clean": 0,
            "Shared_Clean": 0,
            "Referenced": 20,
            "Swap": 0,
            "Private_Dirty": 20,
            "Size": 2097152,
            "Pss": 20,
            "Shared_Dirty": 0,
            "SwapPss": 0,
            "AnonHugePages": 0
          },
          {
            "category": "device_mappings",
            "detail": "/dev/__properties__/u:object_r:build_prop:s0",
            "mapping_count": 1,
            "Anonymous": 0,
            "Rss": 16,
            "Private_Clean": 0,
            "Shared_Clean": 0,
            "Referenced": 16,
            "Swap": 0,
            "Private_Dirty": 0,
            "Size": 128,
            "Pss": 0,
            "Shared_Dirty": 16,
            "SwapPss": 0,
            "AnonHugePages": 0
          },
          {
            "category": "device_mappings",
            "detail": "/dev/__properties__/u:object_r:debug_prop:s0",
            "mapping_count": 2,
            "Anonymous": 0,
            "Rss": 16,
            "Private_Clean": 0,
            "Shared_Clean": 0,
            "Referenced": 16,
            "Swap": 0,
            "Private_Dirty": 0,
            "Size": 256,
            "Pss": 0,
            "Shared_Dirty": 16,
            "SwapPss": 0,
            "AnonHugePages": 0
          },
          {
            "category": "anonymous",
            "detail": "[anon:stack_and_tls:30644]",
            "mapping_count": 1,
            "Anonymous": 12,
            "Rss": 12,
            "Private_Clean": 0,
            "Shared_Clean": 0,
            "Referenced": 12,
            "Swap": 0,
            "Private_Dirty": 12,
            "Size": 1008,
            "Pss": 12,
            "Shared_Dirty": 0,
            "SwapPss": 0,
            "AnonHugePages": 0
          },
          {
            "category": "anonymous",
            "detail": "[anon:stack_and_tls:30643]",
            "mapping_count": 1,
            "Anonymous": 12,
            "Rss": 12,
            "Private_Clean": 0,
            "Shared_Clean": 0,
            "Referenced": 12,
            "Swap": 0,
            "Private_Dirty": 12,
            "Size": 1008,
            "Pss": 12,
            "Shared_Dirty": 0,
            "SwapPss": 0,
            "AnonHugePages": 0
          },
          {
            "category": "anonymous",
            "detail": "[anon:stack_and_tls:30642]",
            "mapping_count": 1,
            "Anonymous": 12,
            "Rss": 12,
            "Private_Clean": 0,
            "Shared_Clean": 0,
            "Referenced": 12,
            "Swap": 0,
            "Private_Dirty": 12,
            "Size": 1008,
            "Pss": 12,
            "Shared_Dirty": 0,
            "SwapPss": 0,
            "AnonHugePages": 0
          },
          {
            "category": "anonymous",
            "detail": "[anon:stack_and_tls:30641]",
            "mapping_count": 1,
            "Anonymous": 12,
            "Rss": 12,
            "Private_Clean": 0,
            "Shared_Clean": 0,
            "Referenced": 12,
            "Swap": 0,
            "Private_Dirty": 12,
            "Size": 1008,
            "Pss": 12,
            "Shared_Dirty": 0,
            "SwapPss": 0,
            "AnonHugePages": 0
          },
          {
            "category": "anonymous",
            "detail": "[anon:stack_and_tls:30640]",
            "mapping_count": 1,
            "Anonymous": 12,
            "Rss": 12,
            "Private_Clean": 0,
            "Shared_Clean": 0,
            "Referenced": 12,
            "Swap": 0,
            "Private_Dirty": 12,
            "Size": 1008,
            "Pss": 12,
            "Shared_Dirty": 0,
            "SwapPss": 0,
            "AnonHugePages": 0
          },
          {
            "category": "anonymous",
            "detail": "[anon:stack_and_tls:30639]",
            "mapping_count": 1,
            "Anonymous": 12,
            "Rss": 12,
            "Private_Clean": 0,
            "Shared_Clean": 0,
            "Referenced": 12,
            "Swap": 0,
            "Private_Dirty": 12,
            "Size": 1008,
            "Pss": 12,
            "Shared_Dirty": 0,
            "SwapPss": 0,
            "AnonHugePages": 0
          },
          {
            "category": "anonymous",
            "detail": "[anon:stack_and_tls:30638]",
            "mapping_count": 1,
            "Anonymous": 12,
            "Rss": 12,
            "Private_Clean": 0,
            "Shared_Clean": 0,
            "Referenced": 12,
            "Swap": 0,
            "Private_Dirty": 12,
            "Size": 1008,
            "Pss": 12,
            "Shared_Dirty": 0,
            "SwapPss": 0,
            "AnonHugePages": 0
          },
          {
            "category": "anonymous",
            "detail": "[anon:stack_and_tls:30636]",
            "mapping_count": 1,
            "Anonymous": 12,
            "Rss": 12,
            "Private_Clean": 0,
            "Shared_Clean": 0,
            "Referenced": 12,
            "Swap": 0,
            "Private_Dirty": 12,
            "Size": 1008,
            "Pss": 12,
            "Shared_Dirty": 0,
            "SwapPss": 0,
            "AnonHugePages": 0
          },
          {
            "category": "anonymous",
            "detail": "[anon:stack_and_tls:30635]",
            "mapping_count": 1,
            "Anonymous": 12,
            "Rss": 12,
            "Private_Clean": 0,
            "Shared_Clean": 0,
            "Referenced": 12,
            "Swap": 0,
            "Private_Dirty": 12,
            "Size": 1008,
            "Pss": 12,
            "Shared_Dirty": 0,
            "SwapPss": 0,
            "AnonHugePages": 0
          },
          {
            "category": "anonymous",
            "detail": "[anon:stack_and_tls:30634]",
            "mapping_count": 1,
            "Anonymous": 12,
            "Rss": 12,
            "Private_Clean": 0,
            "Shared_Clean": 0,
            "Referenced": 12,
            "Swap": 0,
            "Private_Dirty": 12,
            "Size": 1008,
            "Pss": 12,
            "Shared_Dirty": 0,
            "SwapPss": 0,
            "AnonHugePages": 0
          },
          {
            "category": "anonymous",
            "detail": "[anon:stack_and_tls:30633]",
            "mapping_count": 1,
            "Anonymous": 12,
            "Rss": 12,
            "Private_Clean": 0,
            "Shared_Clean": 0,
            "Referenced": 12,
            "Swap": 0,
            "Private_Dirty": 12,
            "Size": 1008,
            "Pss": 12,
            "Shared_Dirty": 0,
            "SwapPss": 0,
            "AnonHugePages": 0
          },
          {
            "category": "anonymous",
            "detail": "[anon:stack_and_tls:30632]",
            "mapping_count": 1,
            "Anonymous": 12,
            "Rss": 12,
            "Private_Clean": 0,
            "Shared_Clean": 0,
            "Referenced": 12,
            "Swap": 0,
            "Private_Dirty": 12,
            "Size": 1008,
            "Pss": 12,
            "Shared_Dirty": 0,
            "SwapPss": 0,
            "AnonHugePages": 0
          },
          {
            "category": "anonymous",
            "detail": "[anon:stack_and_tls:30631]",
            "mapping_count": 1,
            "Anonymous": 12,
            "Rss": 12,
            "Private_Clean": 0,
            "Shared_Clean": 0,
            "Referenced": 12,
            "Swap": 0,
            "Private_Dirty": 12,
            "Size": 1008,
            "Pss": 12,
            "Shared_Dirty": 0,
            "SwapPss": 0,
            "AnonHugePages": 0
          },
          {
            "category": "anonymous",
            "detail": "[anon:stack_and_tls:30630]",
            "mapping_count": 1,
            "Anonymous": 12,
            "Rss": 12,
            "Private_Clean": 0,
            "Shared_Clean": 0,
            "Referenced": 12,
            "Swap": 0,
            "Private_Dirty": 12,
            "Size": 1008,
            "Pss": 12,
            "Shared_Dirty": 0,
            "SwapPss": 0,
            "AnonHugePages": 0
          },
          {
            "category": "anonymous",
            "detail": "[anon:stack_and_tls:30587]",
            "mapping_count": 1,
            "Anonymous": 12,
            "Rss": 12,
            "Private_Clean": 0,
            "Shared_Clean": 0,
            "Referenced": 12,
            "Swap": 0,
            "Private_Dirty": 12,
            "Size": 1008,
            "Pss": 12,
            "Shared_Dirty": 0,
            "SwapPss": 0,
            "AnonHugePages": 0
          },
          {
            "category": "shared_libraries",
            "detail": "libdl.so",
            "mapping_count": 3,
            "Anonymous": 4,
            "Rss": 12,
            "Private_Clean": 0,
            "Shared_Clean": 8,
            "Referenced": 12,
            "Swap": 0,
            "Private_Dirty": 4,
            "Size": 12,
            "Pss": 4,
            "Shared_Dirty": 0,
            "SwapPss": 0,
            "AnonHugePages": 0
          },
          {
            "category": "anonymous",
            "detail": "[anon:stack_and_tls:main]",
            "mapping_count": 1,
            "Anonymous": 12,
            "Rss": 12,
            "Private_Clean": 0,
            "Shared_Clean": 0,
            "Referenced": 12,
            "Swap": 0,
            "Private_Dirty": 12,
            "Size": 16,
            "Pss": 12,
            "Shared_Dirty": 0,
            "SwapPss": 0,
            "AnonHugePages": 0
          },
          {
            "category": "device_mappings",
            "detail": "/dev/__properties__/properties_serial",
            "mapping_count": 2,
            "Anonymous": 0,
            "Rss": 8,
            "Private_Clean": 0,
            "Shared_Clean": 0,
            "Referenced": 8,
            "Swap": 0,
            "Private_Dirty": 0,
            "Size": 256,
            "Pss": 0,
            "Shared_Dirty": 8,
            "SwapPss": 0,
            "AnonHugePages": 0
          },
          {
            "category": "anonymous",
            "detail": "[anon:atexit handlers]",
            "mapping_count": 2,
            "Anonymous": 8,
            "Rss": 8,
            "Private_Clean": 0,
            "Shared_Clean": 0,
            "Referenced": 8,
            "Swap": 0,
            "Private_Dirty": 8,
            "Size": 8,
            "Pss": 8,
            "Shared_Dirty": 0,
            "SwapPss": 0,
            "AnonHugePages": 0
          },
          {
            "category": "anonymous",
            "detail": "[anon:arc4random data]",
            "mapping_count": 2,
            "Anonymous": 8,
            "Rss": 8,
            "Private_Clean": 0,
            "Shared_Clean": 0,
            "Referenced": 8,
            "Swap": 0,
            "Private_Dirty": 8,
            "Size": 8,
            "Pss": 8,
            "Shared_Dirty": 0,
            "SwapPss": 0,
            "AnonHugePages": 0
          },
          {
            "category": "device_mappings",
            "detail": "/dev/__properties__/u:object_r:heapprofd_prop:s0",
            "mapping_count": 1,
            "Anonymous": 0,
            "Rss": 4,
            "Private_Clean": 0,
            "Shared_Clean": 0,
            "Referenced": 4,
            "Swap": 0,
            "Private_Dirty": 0,
            "Size": 128,
            "Pss": 0,
            "Shared_Dirty": 4,
            "SwapPss": 0,
            "AnonHugePages": 0
          },
          {
            "category": "device_mappings",
            "detail": "/dev/__properties__/u:object_r:libc_debug_prop:s0",
            "mapping_count": 1,
            "Anonymous": 0,
            "Rss": 4,
            "Private_Clean": 0,
            "Shared_Clean": 0,
            "Referenced": 4,
            "Swap": 0,
            "Private_Dirty": 0,
            "Size": 128,
            "Pss": 0,
            "Shared_Dirty": 4,
            "SwapPss": 0,
            "AnonHugePages": 0
          },
          {
            "category": "device_mappings",
            "detail": "/dev/__properties__/u:object_r:gwp_asan_prop:s0",
            "mapping_count": 1,
            "Anonymous": 0,
            "Rss": 4,
            "Private_Clean": 0,
            "Shared_Clean": 0,
            "Referenced": 4,
            "Swap": 0,
            "Private_Dirty": 0,
            "Size": 128,
            "Pss": 0,
            "Shared_Dirty": 4,
            "SwapPss": 0,
            "AnonHugePages": 0
          },
          {
            "category": "device_mappings",
            "detail": "/dev/__properties__/u:object_r:vendor_socket_hook_prop:s0",
            "mapping_count": 1,
            "Anonymous": 0,
            "Rss": 4,
            "Private_Clean": 0,
            "Shared_Clean": 0,
            "Referenced": 4,
            "Swap": 0,
            "Private_Dirty": 0,
            "Size": 128,
            "Pss": 0,
            "Shared_Dirty": 4,
            "SwapPss": 0,
            "AnonHugePages": 0
          },
          {
            "category": "device_mappings",
            "detail": "/dev/__properties__/u:object_r:vndk_prop:s0",
            "mapping_count": 1,
            "Anonymous": 0,
            "Rss": 4,
            "Private_Clean": 0,
            "Shared_Clean": 0,
            "Referenced": 4,
            "Swap": 0,
            "Private_Dirty": 0,
            "Size": 128,
            "Pss": 0,
            "Shared_Dirty": 4,
            "SwapPss": 0,
            "AnonHugePages": 0
          },
          {
            "category": "special_mappings",
            "detail": "[vdso]",
            "mapping_count": 1,
            "Anonymous": 0,
            "Rss": 4,
            "Private_Clean": 0,
            "Shared_Clean": 4,
            "Referenced": 4,
            "Swap": 0,
            "Private_Dirty": 0,
            "Size": 8,
            "Pss": 0,
            "Shared_Dirty": 0,
            "SwapPss": 0,
            "AnonHugePages": 0
          },
          {
            "category": "anonymous",
            "detail": "<anonymous>",
            "mapping_count": 201,
            "Anonymous": 0,
            "Rss": 0,
            "Private_Clean": 0,
            "Shared_Clean": 0,
            "Referenced": 0,
            "Swap": 0,
            "Private_Dirty": 0,
            "Size": 413336,
            "Pss": 0,
            "Shared_Dirty": 0,
            "SwapPss": 0,
            "AnonHugePages": 0
          },
          {
            "category": "anonymous",
            "detail": "[anon:thread signal stack]",
            "mapping_count": 17,
            "Anonymous": 0,
            "Rss": 0,
            "Private_Clean": 0,
            "Shared_Clean": 0,
            "Referenced": 0,
            "Swap": 0,
            "Private_Dirty": 0,
            "Size": 544,
            "Pss": 0,
            "Shared_Dirty": 0,
            "SwapPss": 0,
            "AnonHugePages": 0
          },
          {
            "category": "anonymous",
            "detail": "[anon:scudo:primary_reserve]",
            "mapping_count": 34,
            "Anonymous": 0,
            "Rss": 0,
            "Private_Clean": 0,
            "Shared_Clean": 0,
            "Referenced": 0,
            "Swap": 0,
            "Private_Dirty": 0,
            "Size": 8620800,
            "Pss": 0,
            "Shared_Dirty": 0,
            "SwapPss": 0,
            "AnonHugePages": 0
          },
          {
            "category": "special_mappings",
            "detail": "[page size compat]",
            "mapping_count": 6,
            "Anonymous": 0,
            "Rss": 0,
            "Private_Clean": 0,
            "Shared_Clean": 0,
            "Referenced": 0,
            "Swap": 0,
            "Private_Dirty": 0,
            "Size": 48,
            "Pss": 0,
            "Shared_Dirty": 0,
            "SwapPss": 0,
            "AnonHugePages": 0
          },
          {
            "category": "special_mappings",
            "detail": "[vvar]",
            "mapping_count": 1,
            "Anonymous": 0,
            "Rss": 0,
            "Private_Clean": 0,
            "Shared_Clean": 0,
            "Referenced": 0,
            "Swap": 0,
            "Private_Dirty": 0,
            "Size": 8,
            "Pss": 0,
            "Shared_Dirty": 0,
            "SwapPss": 0,
            "AnonHugePages": 0
          }
        ]
      }
    },
    "active_peak": {
      "captured_utc": "2026-07-17T05:24:20.491219+00:00",
      "pid": 30577,
      "summary": {
        "status": {
          "Name": "liblfmserver.so",
          "Umask": "0077",
          "State": "S (sleeping)",
          "Tgid": "30577",
          "Ngid": "0",
          "Pid": "30577",
          "PPid": "30487",
          "TracerPid": "0",
          "Uid": "10538\t10538\t10538\t10538",
          "Gid": "10538\t10538\t10538\t10538",
          "FDSize": "256",
          "Groups": "3003 9997 20538 50538 99909997",
          "Kthread": "0",
          "VmPeak": 14084892,
          "VmSize": 13966404,
          "VmLck": 0,
          "VmPin": 0,
          "VmHWM": 1914780,
          "VmRSS": 1914780,
          "RssAnon": 1190456,
          "RssFile": 724024,
          "RssShmem": 300,
          "VmData": 2088688,
          "VmStk": 136,
          "VmExe": 1220,
          "VmLib": 9744,
          "VmPTE": 4120,
          "VmSwap": 0,
          "CoreDumping": "0",
          "THP_enabled": "1",
          "untag_mask": "0xffffffffffffff",
          "Threads": "18",
          "SigQ": "0/57649",
          "SigPnd": "0000000000000000",
          "ShdPnd": "0000000000000000",
          "SigBlk": "0000000080001204",
          "SigIgn": "0000002000001001",
          "SigCgt": "0000004c400084fa",
          "CapInh": "0000000000000000",
          "CapPrm": "0000000000000000",
          "CapEff": "0000000000000000",
          "CapBnd": "0000000000000000",
          "CapAmb": "0000000000000000",
          "NoNewPrivs": "0",
          "Seccomp": "2",
          "Seccomp_filters": "1",
          "Speculation_Store_Bypass": "thread vulnerable",
          "SpeculationIndirectBranch": "unknown",
          "Cpus_allowed": "ff",
          "Cpus_allowed_list": "0-7",
          "Mems_allowed": "1",
          "Mems_allowed_list": "0",
          "voluntary_ctxt_switches": "24",
          "nonvoluntary_ctxt_switches": "163"
        },
        "smaps_totals_kib": {
          "Anonymous": 1190996,
          "Rss": 1915544,
          "Private_Clean": 721548,
          "Shared_Clean": 2672,
          "Referenced": 1915492,
          "Swap": 0,
          "Private_Dirty": 1190996,
          "Size": 13966404,
          "Pss": 1912559,
          "Shared_Dirty": 328,
          "SwapPss": 0,
          "AnonHugePages": 387072
        },
        "category_totals_kib": {
          "anonymous": {
            "Anonymous": 1190656,
            "Rss": 1190656,
            "Private_Clean": 0,
            "Shared_Clean": 0,
            "Referenced": 1190656,
            "Swap": 0,
            "Private_Dirty": 1190656,
            "Size": 13237908,
            "Pss": 1190656,
            "Shared_Dirty": 0,
            "SwapPss": 0,
            "AnonHugePages": 387072
          },
          "gguf_weights": {
            "Anonymous": 0,
            "Rss": 714380,
            "Private_Clean": 714380,
            "Shared_Clean": 0,
            "Referenced": 714380,
            "Swap": 0,
            "Private_Dirty": 0,
            "Size": 714380,
            "Pss": 714380,
            "Shared_Dirty": 0,
            "SwapPss": 0,
            "AnonHugePages": 0
          },
          "shared_libraries": {
            "Anonymous": 296,
            "Rss": 9260,
            "Private_Clean": 7168,
            "Shared_Clean": 1796,
            "Referenced": 9208,
            "Swap": 0,
            "Private_Dirty": 296,
            "Size": 11000,
            "Pss": 7472,
            "Shared_Dirty": 0,
            "SwapPss": 0,
            "AnonHugePages": 0
          },
          "other_file_backed": {
            "Anonymous": 44,
            "Rss": 916,
            "Private_Clean": 0,
            "Shared_Clean": 872,
            "Referenced": 916,
            "Swap": 0,
            "Private_Dirty": 44,
            "Size": 1492,
            "Pss": 51,
            "Shared_Dirty": 0,
            "SwapPss": 0,
            "AnonHugePages": 0
          },
          "device_mappings": {
            "Anonymous": 0,
            "Rss": 328,
            "Private_Clean": 0,
            "Shared_Clean": 0,
            "Referenced": 328,
            "Swap": 0,
            "Private_Dirty": 0,
            "Size": 1560,
            "Pss": 0,
            "Shared_Dirty": 328,
            "SwapPss": 0,
            "AnonHugePages": 0
          },
          "special_mappings": {
            "Anonymous": 0,
            "Rss": 4,
            "Private_Clean": 0,
            "Shared_Clean": 4,
            "Referenced": 4,
            "Swap": 0,
            "Private_Dirty": 0,
            "Size": 64,
            "Pss": 0,
            "Shared_Dirty": 0,
            "SwapPss": 0,
            "AnonHugePages": 0
          }
        },
        "rows": [
          {
            "category": "anonymous",
            "detail": "[anon:scudo:secondary]",
            "mapping_count": 97,
            "Anonymous": 1165612,
            "Rss": 1165612,
            "Private_Clean": 0,
            "Shared_Clean": 0,
            "Referenced": 1165612,
            "Swap": 0,
            "Private_Dirty": 1165612,
            "Size": 2039168,
            "Pss": 1165612,
            "Shared_Dirty": 0,
            "SwapPss": 0,
            "AnonHugePages": 387072
          },
          {
            "category": "gguf_weights",
            "detail": "LFM2.5-Audio-1.5B-Q4_0.gguf",
            "mapping_count": 2,
            "Anonymous": 0,
            "Rss": 667908,
            "Private_Clean": 667908,
            "Shared_Clean": 0,
            "Referenced": 667908,
            "Swap": 0,
            "Private_Dirty": 0,
            "Size": 667908,
            "Pss": 667908,
            "Shared_Dirty": 0,
            "SwapPss": 0,
            "AnonHugePages": 0
          },
          {
            "category": "gguf_weights",
            "detail": "tokenizer-LFM2.5-Audio-1.5B-Q4_0.gguf",
            "mapping_count": 2,
            "Anonymous": 0,
            "Rss": 46472,
            "Private_Clean": 46472,
            "Shared_Clean": 0,
            "Referenced": 46472,
            "Swap": 0,
            "Private_Dirty": 0,
            "Size": 46472,
            "Pss": 46472,
            "Shared_Dirty": 0,
            "SwapPss": 0,
            "AnonHugePages": 0
          },
          {
            "category": "anonymous",
            "detail": "[anon:scudo:primary]",
            "mapping_count": 33,
            "Anonymous": 23724,
            "Rss": 23724,
            "Private_Clean": 0,
            "Shared_Clean": 0,
            "Referenced": 23724,
            "Swap": 0,
            "Private_Dirty": 23724,
            "Size": 29952,
            "Pss": 23724,
            "Shared_Dirty": 0,
            "SwapPss": 0,
            "AnonHugePages": 0
          },
          {
            "category": "shared_libraries",
            "detail": "libliquid-audio.so",
            "mapping_count": 3,
            "Anonymous": 48,
            "Rss": 1852,
            "Private_Clean": 1804,
            "Shared_Clean": 0,
            "Referenced": 1852,
            "Swap": 0,
            "Private_Dirty": 48,
            "Size": 2428,
            "Pss": 1852,
            "Shared_Dirty": 0,
            "SwapPss": 0,
            "AnonHugePages": 0
          },
          {
            "category": "shared_libraries",
            "detail": "libllama.so",
            "mapping_count": 3,
            "Anonymous": 48,
            "Rss": 1760,
            "Private_Clean": 1712,
            "Shared_Clean": 0,
            "Referenced": 1760,
            "Swap": 0,
            "Private_Dirty": 48,
            "Size": 2080,
            "Pss": 1760,
            "Shared_Dirty": 0,
            "SwapPss": 0,
            "AnonHugePages": 0
          },
          {
            "category": "shared_libraries",
            "detail": "liblfmserver.so",
            "mapping_count": 3,
            "Anonymous": 28,
            "Rss": 1056,
            "Private_Clean": 1028,
            "Shared_Clean": 0,
            "Referenced": 1056,
            "Swap": 0,
            "Private_Dirty": 28,
            "Size": 1248,
            "Pss": 1056,
            "Shared_Dirty": 0,
            "SwapPss": 0,
            "AnonHugePages": 0
          },
          {
            "category": "other_file_backed",
            "detail": "/apex/com.android.runtime/bin/linker64",
            "mapping_count": 4,
            "Anonymous": 44,
            "Rss": 916,
            "Private_Clean": 0,
            "Shared_Clean": 872,
            "Referenced": 916,
            "Swap": 0,
            "Private_Dirty": 44,
            "Size": 1492,
            "Pss": 51,
            "Shared_Dirty": 0,
            "SwapPss": 0,
            "AnonHugePages": 0
          },
          {
            "category": "shared_libraries",
            "detail": "libggml-base.so",
            "mapping_count": 3,
            "Anonymous": 36,
            "Rss": 868,
            "Private_Clean": 832,
            "Shared_Clean": 0,
            "Referenced": 868,
            "Swap": 0,
            "Private_Dirty": 36,
            "Size": 932,
            "Pss": 868,
            "Shared_Dirty": 0,
            "SwapPss": 0,
            "AnonHugePages": 0
          },
          {
            "category": "shared_libraries",
            "detail": "libc++.so",
            "mapping_count": 4,
            "Anonymous": 36,
            "Rss": 820,
            "Private_Clean": 0,
            "Shared_Clean": 784,
            "Referenced": 768,
            "Swap": 0,
            "Private_Dirty": 36,
            "Size": 1028,
            "Pss": 39,
            "Shared_Dirty": 0,
            "SwapPss": 0,
            "AnonHugePages": 0
          },
          {
            "category": "shared_libraries",
            "detail": "libc.so",
            "mapping_count": 4,
            "Anonymous": 20,
            "Rss": 784,
            "Private_Clean": 0,
            "Shared_Clean": 764,
            "Referenced": 784,
            "Swap": 0,
            "Private_Dirty": 20,
            "Size": 960,
            "Pss": 21,
            "Shared_Dirty": 0,
            "SwapPss": 0,
            "AnonHugePages": 0
          },
          {
            "category": "anonymous",
            "detail": "[anon:.bss]",
            "mapping_count": 16,
            "Anonymous": 712,
            "Rss": 712,
            "Private_Clean": 0,
            "Shared_Clean": 0,
            "Referenced": 712,
            "Swap": 0,
            "Private_Dirty": 712,
            "Size": 944,
            "Pss": 712,
            "Shared_Dirty": 0,
            "SwapPss": 0,
            "AnonHugePages": 0
          },
          {
            "category": "shared_libraries",
            "detail": "libggml.so",
            "mapping_count": 3,
            "Anonymous": 28,
            "Rss": 660,
            "Private_Clean": 632,
            "Shared_Clean": 0,
            "Referenced": 660,
            "Swap": 0,
            "Private_Dirty": 28,
            "Size": 660,
            "Pss": 660,
            "Shared_Dirty": 0,
            "SwapPss": 0,
            "AnonHugePages": 0
          },
          {
            "category": "shared_libraries",
            "detail": "libggml-cpu-android_armv8.6_1.so",
            "mapping_count": 3,
            "Anonymous": 16,
            "Rss": 636,
            "Private_Clean": 620,
            "Shared_Clean": 0,
            "Referenced": 636,
            "Swap": 0,
            "Private_Dirty": 16,
            "Size": 700,
            "Pss": 636,
            "Shared_Dirty": 0,
            "SwapPss": 0,
            "AnonHugePages": 0
          },
          {
            "category": "shared_libraries",
            "detail": "libmtmd.so",
            "mapping_count": 3,
            "Anonymous": 16,
            "Rss": 556,
            "Private_Clean": 540,
            "Shared_Clean": 0,
            "Referenced": 556,
            "Swap": 0,
            "Private_Dirty": 16,
            "Size": 684,
            "Pss": 556,
            "Shared_Dirty": 0,
            "SwapPss": 0,
            "AnonHugePages": 0
          },
          {
            "category": "device_mappings",
            "detail": "/dev/__properties__/property_info",
            "mapping_count": 2,
            "Anonymous": 0,
            "Rss": 268,
            "Private_Clean": 0,
            "Shared_Clean": 0,
            "Referenced": 268,
            "Swap": 0,
            "Private_Dirty": 0,
            "Size": 280,
            "Pss": 0,
            "Shared_Dirty": 268,
            "SwapPss": 0,
            "AnonHugePages": 0
          },
          {
            "category": "shared_libraries",
            "detail": "libm.so",
            "mapping_count": 4,
            "Anonymous": 8,
            "Rss": 216,
            "Private_Clean": 0,
            "Shared_Clean": 208,
            "Referenced": 216,
            "Swap": 0,
            "Private_Dirty": 8,
            "Size": 228,
            "Pss": 12,
            "Shared_Dirty": 0,
            "SwapPss": 0,
            "AnonHugePages": 0
          },
          {
            "category": "anonymous",
            "detail": "[anon:bionic_alloc_small_objects]",
            "mapping_count": 14,
            "Anonymous": 116,
            "Rss": 116,
            "Private_Clean": 0,
            "Shared_Clean": 0,
            "Referenced": 116,
            "Swap": 0,
            "Private_Dirty": 116,
            "Size": 116,
            "Pss": 116,
            "Shared_Dirty": 0,
            "SwapPss": 0,
            "AnonHugePages": 0
          },
          {
            "category": "anonymous",
            "detail": "[stack]",
            "mapping_count": 1,
            "Anonymous": 92,
            "Rss": 92,
            "Private_Clean": 0,
            "Shared_Clean": 0,
            "Referenced": 92,
            "Swap": 0,
            "Private_Dirty": 92,
            "Size": 136,
            "Pss": 92,
            "Shared_Dirty": 0,
            "SwapPss": 0,
            "AnonHugePages": 0
          },
          {
            "category": "anonymous",
            "detail": "[anon:stack_and_tls:30663]",
            "mapping_count": 1,
            "Anonymous": 52,
            "Rss": 52,
            "Private_Clean": 0,
            "Shared_Clean": 0,
            "Referenced": 52,
            "Swap": 0,
            "Private_Dirty": 52,
            "Size": 1008,
            "Pss": 52,
            "Shared_Dirty": 0,
            "SwapPss": 0,
            "AnonHugePages": 0
          },
          {
            "category": "anonymous",
            "detail": "[anon:System property context nodes]",
            "mapping_count": 2,
            "Anonymous": 48,
            "Rss": 48,
            "Private_Clean": 0,
            "Shared_Clean": 0,
            "Referenced": 48,
            "Swap": 0,
            "Private_Dirty": 48,
            "Size": 48,
            "Pss": 48,
            "Shared_Dirty": 0,
            "SwapPss": 0,
            "AnonHugePages": 0
          },
          {
            "category": "shared_libraries",
            "detail": "libnetd_client.so",
            "mapping_count": 4,
            "Anonymous": 8,
            "Rss": 40,
            "Private_Clean": 0,
            "Shared_Clean": 32,
            "Referenced": 40,
            "Swap": 0,
            "Private_Dirty": 8,
            "Size": 40,
            "Pss": 8,
            "Shared_Dirty": 0,
            "SwapPss": 0,
            "AnonHugePages": 0
          },
          {
            "category": "anonymous",
            "detail": "[anon:stack_and_tls:30641]",
            "mapping_count": 1,
            "Anonymous": 36,
            "Rss": 36,
            "Private_Clean": 0,
            "Shared_Clean": 0,
            "Referenced": 36,
            "Swap": 0,
            "Private_Dirty": 36,
            "Size": 1008,
            "Pss": 36,
            "Shared_Dirty": 0,
            "SwapPss": 0,
            "AnonHugePages": 0
          },
          {
            "category": "anonymous",
            "detail": "[anon:linker_alloc]",
            "mapping_count": 4,
            "Anonymous": 28,
            "Rss": 28,
            "Private_Clean": 0,
            "Shared_Clean": 0,
            "Referenced": 28,
            "Swap": 0,
            "Private_Dirty": 28,
            "Size": 1920,
            "Pss": 28,
            "Shared_Dirty": 0,
            "SwapPss": 0,
            "AnonHugePages": 0
          },
          {
            "category": "anonymous",
            "detail": "[anon:stack_and_tls:30637]",
            "mapping_count": 1,
            "Anonymous": 20,
            "Rss": 20,
            "Private_Clean": 0,
            "Shared_Clean": 0,
            "Referenced": 20,
            "Swap": 0,
            "Private_Dirty": 20,
            "Size": 1008,
            "Pss": 20,
            "Shared_Dirty": 0,
            "SwapPss": 0,
            "AnonHugePages": 0
          },
          {
            "category": "anonymous",
            "detail": "[anon:cfi shadow]",
            "mapping_count": 10,
            "Anonymous": 20,
            "Rss": 20,
            "Private_Clean": 0,
            "Shared_Clean": 0,
            "Referenced": 20,
            "Swap": 0,
            "Private_Dirty": 20,
            "Size": 2097152,
            "Pss": 20,
            "Shared_Dirty": 0,
            "SwapPss": 0,
            "AnonHugePages": 0
          },
          {
            "category": "device_mappings",
            "detail": "/dev/__properties__/u:object_r:build_prop:s0",
            "mapping_count": 1,
            "Anonymous": 0,
            "Rss": 16,
            "Private_Clean": 0,
            "Shared_Clean": 0,
            "Referenced": 16,
            "Swap": 0,
            "Private_Dirty": 0,
            "Size": 128,
            "Pss": 0,
            "Shared_Dirty": 16,
            "SwapPss": 0,
            "AnonHugePages": 0
          },
          {
            "category": "device_mappings",
            "detail": "/dev/__properties__/u:object_r:debug_prop:s0",
            "mapping_count": 2,
            "Anonymous": 0,
            "Rss": 16,
            "Private_Clean": 0,
            "Shared_Clean": 0,
            "Referenced": 16,
            "Swap": 0,
            "Private_Dirty": 0,
            "Size": 256,
            "Pss": 0,
            "Shared_Dirty": 16,
            "SwapPss": 0,
            "AnonHugePages": 0
          },
          {
            "category": "anonymous",
            "detail": "[anon:stack_and_tls:30644]",
            "mapping_count": 1,
            "Anonymous": 12,
            "Rss": 12,
            "Private_Clean": 0,
            "Shared_Clean": 0,
            "Referenced": 12,
            "Swap": 0,
            "Private_Dirty": 12,
            "Size": 1008,
            "Pss": 12,
            "Shared_Dirty": 0,
            "SwapPss": 0,
            "AnonHugePages": 0
          },
          {
            "category": "anonymous",
            "detail": "[anon:stack_and_tls:30643]",
            "mapping_count": 1,
            "Anonymous": 12,
            "Rss": 12,
            "Private_Clean": 0,
            "Shared_Clean": 0,
            "Referenced": 12,
            "Swap": 0,
            "Private_Dirty": 12,
            "Size": 1008,
            "Pss": 12,
            "Shared_Dirty": 0,
            "SwapPss": 0,
            "AnonHugePages": 0
          },
          {
            "category": "anonymous",
            "detail": "[anon:stack_and_tls:30642]",
            "mapping_count": 1,
            "Anonymous": 12,
            "Rss": 12,
            "Private_Clean": 0,
            "Shared_Clean": 0,
            "Referenced": 12,
            "Swap": 0,
            "Private_Dirty": 12,
            "Size": 1008,
            "Pss": 12,
            "Shared_Dirty": 0,
            "SwapPss": 0,
            "AnonHugePages": 0
          },
          {
            "category": "anonymous",
            "detail": "[anon:stack_and_tls:30640]",
            "mapping_count": 1,
            "Anonymous": 12,
            "Rss": 12,
            "Private_Clean": 0,
            "Shared_Clean": 0,
            "Referenced": 12,
            "Swap": 0,
            "Private_Dirty": 12,
            "Size": 1008,
            "Pss": 12,
            "Shared_Dirty": 0,
            "SwapPss": 0,
            "AnonHugePages": 0
          },
          {
            "category": "anonymous",
            "detail": "[anon:stack_and_tls:30639]",
            "mapping_count": 1,
            "Anonymous": 12,
            "Rss": 12,
            "Private_Clean": 0,
            "Shared_Clean": 0,
            "Referenced": 12,
            "Swap": 0,
            "Private_Dirty": 12,
            "Size": 1008,
            "Pss": 12,
            "Shared_Dirty": 0,
            "SwapPss": 0,
            "AnonHugePages": 0
          },
          {
            "category": "anonymous",
            "detail": "[anon:stack_and_tls:30638]",
            "mapping_count": 1,
            "Anonymous": 12,
            "Rss": 12,
            "Private_Clean": 0,
            "Shared_Clean": 0,
            "Referenced": 12,
            "Swap": 0,
            "Private_Dirty": 12,
            "Size": 1008,
            "Pss": 12,
            "Shared_Dirty": 0,
            "SwapPss": 0,
            "AnonHugePages": 0
          },
          {
            "category": "anonymous",
            "detail": "[anon:stack_and_tls:30636]",
            "mapping_count": 1,
            "Anonymous": 12,
            "Rss": 12,
            "Private_Clean": 0,
            "Shared_Clean": 0,
            "Referenced": 12,
            "Swap": 0,
            "Private_Dirty": 12,
            "Size": 1008,
            "Pss": 12,
            "Shared_Dirty": 0,
            "SwapPss": 0,
            "AnonHugePages": 0
          },
          {
            "category": "anonymous",
            "detail": "[anon:stack_and_tls:30635]",
            "mapping_count": 1,
            "Anonymous": 12,
            "Rss": 12,
            "Private_Clean": 0,
            "Shared_Clean": 0,
            "Referenced": 12,
            "Swap": 0,
            "Private_Dirty": 12,
            "Size": 1008,
            "Pss": 12,
            "Shared_Dirty": 0,
            "SwapPss": 0,
            "AnonHugePages": 0
          },
          {
            "category": "anonymous",
            "detail": "[anon:stack_and_tls:30634]",
            "mapping_count": 1,
            "Anonymous": 12,
            "Rss": 12,
            "Private_Clean": 0,
            "Shared_Clean": 0,
            "Referenced": 12,
            "Swap": 0,
            "Private_Dirty": 12,
            "Size": 1008,
            "Pss": 12,
            "Shared_Dirty": 0,
            "SwapPss": 0,
            "AnonHugePages": 0
          },
          {
            "category": "anonymous",
            "detail": "[anon:stack_and_tls:30633]",
            "mapping_count": 1,
            "Anonymous": 12,
            "Rss": 12,
            "Private_Clean": 0,
            "Shared_Clean": 0,
            "Referenced": 12,
            "Swap": 0,
            "Private_Dirty": 12,
            "Size": 1008,
            "Pss": 12,
            "Shared_Dirty": 0,
            "SwapPss": 0,
            "AnonHugePages": 0
          },
          {
            "category": "anonymous",
            "detail": "[anon:stack_and_tls:30632]",
            "mapping_count": 1,
            "Anonymous": 12,
            "Rss": 12,
            "Private_Clean": 0,
            "Shared_Clean": 0,
            "Referenced": 12,
            "Swap": 0,
            "Private_Dirty": 12,
            "Size": 1008,
            "Pss": 12,
            "Shared_Dirty": 0,
            "SwapPss": 0,
            "AnonHugePages": 0
          },
          {
            "category": "anonymous",
            "detail": "[anon:stack_and_tls:30631]",
            "mapping_count": 1,
            "Anonymous": 12,
            "Rss": 12,
            "Private_Clean": 0,
            "Shared_Clean": 0,
            "Referenced": 12,
            "Swap": 0,
            "Private_Dirty": 12,
            "Size": 1008,
            "Pss": 12,
            "Shared_Dirty": 0,
            "SwapPss": 0,
            "AnonHugePages": 0
          },
          {
            "category": "anonymous",
            "detail": "[anon:stack_and_tls:30630]",
            "mapping_count": 1,
            "Anonymous": 12,
            "Rss": 12,
            "Private_Clean": 0,
            "Shared_Clean": 0,
            "Referenced": 12,
            "Swap": 0,
            "Private_Dirty": 12,
            "Size": 1008,
            "Pss": 12,
            "Shared_Dirty": 0,
            "SwapPss": 0,
            "AnonHugePages": 0
          },
          {
            "category": "anonymous",
            "detail": "[anon:stack_and_tls:30587]",
            "mapping_count": 1,
            "Anonymous": 12,
            "Rss": 12,
            "Private_Clean": 0,
            "Shared_Clean": 0,
            "Referenced": 12,
            "Swap": 0,
            "Private_Dirty": 12,
            "Size": 1008,
            "Pss": 12,
            "Shared_Dirty": 0,
            "SwapPss": 0,
            "AnonHugePages": 0
          },
          {
            "category": "shared_libraries",
            "detail": "libdl.so",
            "mapping_count": 3,
            "Anonymous": 4,
            "Rss": 12,
            "Private_Clean": 0,
            "Shared_Clean": 8,
            "Referenced": 12,
            "Swap": 0,
            "Private_Dirty": 4,
            "Size": 12,
            "Pss": 4,
            "Shared_Dirty": 0,
            "SwapPss": 0,
            "AnonHugePages": 0
          },
          {
            "category": "anonymous",
            "detail": "[anon:stack_and_tls:main]",
            "mapping_count": 1,
            "Anonymous": 12,
            "Rss": 12,
            "Private_Clean": 0,
            "Shared_Clean": 0,
            "Referenced": 12,
            "Swap": 0,
            "Private_Dirty": 12,
            "Size": 16,
            "Pss": 12,
            "Shared_Dirty": 0,
            "SwapPss": 0,
            "AnonHugePages": 0
          },
          {
            "category": "device_mappings",
            "detail": "/dev/__properties__/properties_serial",
            "mapping_count": 2,
            "Anonymous": 0,
            "Rss": 8,
            "Private_Clean": 0,
            "Shared_Clean": 0,
            "Referenced": 8,
            "Swap": 0,
            "Private_Dirty": 0,
            "Size": 256,
            "Pss": 0,
            "Shared_Dirty": 8,
            "SwapPss": 0,
            "AnonHugePages": 0
          },
          {
            "category": "anonymous",
            "detail": "[anon:atexit handlers]",
            "mapping_count": 2,
            "Anonymous": 8,
            "Rss": 8,
            "Private_Clean": 0,
            "Shared_Clean": 0,
            "Referenced": 8,
            "Swap": 0,
            "Private_Dirty": 8,
            "Size": 8,
            "Pss": 8,
            "Shared_Dirty": 0,
            "SwapPss": 0,
            "AnonHugePages": 0
          },
          {
            "category": "anonymous",
            "detail": "[anon:arc4random data]",
            "mapping_count": 2,
            "Anonymous": 8,
            "Rss": 8,
            "Private_Clean": 0,
            "Shared_Clean": 0,
            "Referenced": 8,
            "Swap": 0,
            "Private_Dirty": 8,
            "Size": 8,
            "Pss": 8,
            "Shared_Dirty": 0,
            "SwapPss": 0,
            "AnonHugePages": 0
          },
          {
            "category": "device_mappings",
            "detail": "/dev/__properties__/u:object_r:heapprofd_prop:s0",
            "mapping_count": 1,
            "Anonymous": 0,
            "Rss": 4,
            "Private_Clean": 0,
            "Shared_Clean": 0,
            "Referenced": 4,
            "Swap": 0,
            "Private_Dirty": 0,
            "Size": 128,
            "Pss": 0,
            "Shared_Dirty": 4,
            "SwapPss": 0,
            "AnonHugePages": 0
          },
          {
            "category": "device_mappings",
            "detail": "/dev/__properties__/u:object_r:libc_debug_prop:s0",
            "mapping_count": 1,
            "Anonymous": 0,
            "Rss": 4,
            "Private_Clean": 0,
            "Shared_Clean": 0,
            "Referenced": 4,
            "Swap": 0,
            "Private_Dirty": 0,
            "Size": 128,
            "Pss": 0,
            "Shared_Dirty": 4,
            "SwapPss": 0,
            "AnonHugePages": 0
          },
          {
            "category": "device_mappings",
            "detail": "/dev/__properties__/u:object_r:gwp_asan_prop:s0",
            "mapping_count": 1,
            "Anonymous": 0,
            "Rss": 4,
            "Private_Clean": 0,
            "Shared_Clean": 0,
            "Referenced": 4,
            "Swap": 0,
            "Private_Dirty": 0,
            "Size": 128,
            "Pss": 0,
            "Shared_Dirty": 4,
            "SwapPss": 0,
            "AnonHugePages": 0
          },
          {
            "category": "device_mappings",
            "detail": "/dev/__properties__/u:object_r:vendor_socket_hook_prop:s0",
            "mapping_count": 1,
            "Anonymous": 0,
            "Rss": 4,
            "Private_Clean": 0,
            "Shared_Clean": 0,
            "Referenced": 4,
            "Swap": 0,
            "Private_Dirty": 0,
            "Size": 128,
            "Pss": 0,
            "Shared_Dirty": 4,
            "SwapPss": 0,
            "AnonHugePages": 0
          },
          {
            "category": "device_mappings",
            "detail": "/dev/__properties__/u:object_r:vndk_prop:s0",
            "mapping_count": 1,
            "Anonymous": 0,
            "Rss": 4,
            "Private_Clean": 0,
            "Shared_Clean": 0,
            "Referenced": 4,
            "Swap": 0,
            "Private_Dirty": 0,
            "Size": 128,
            "Pss": 0,
            "Shared_Dirty": 4,
            "SwapPss": 0,
            "AnonHugePages": 0
          },
          {
            "category": "special_mappings",
            "detail": "[vdso]",
            "mapping_count": 1,
            "Anonymous": 0,
            "Rss": 4,
            "Private_Clean": 0,
            "Shared_Clean": 4,
            "Referenced": 4,
            "Swap": 0,
            "Private_Dirty": 0,
            "Size": 8,
            "Pss": 0,
            "Shared_Dirty": 0,
            "SwapPss": 0,
            "AnonHugePages": 0
          },
          {
            "category": "anonymous",
            "detail": "<anonymous>",
            "mapping_count": 230,
            "Anonymous": 0,
            "Rss": 0,
            "Private_Clean": 0,
            "Shared_Clean": 0,
            "Referenced": 0,
            "Swap": 0,
            "Private_Dirty": 0,
            "Size": 429928,
            "Pss": 0,
            "Shared_Dirty": 0,
            "SwapPss": 0,
            "AnonHugePages": 0
          },
          {
            "category": "anonymous",
            "detail": "[anon:thread signal stack]",
            "mapping_count": 18,
            "Anonymous": 0,
            "Rss": 0,
            "Private_Clean": 0,
            "Shared_Clean": 0,
            "Referenced": 0,
            "Swap": 0,
            "Private_Dirty": 0,
            "Size": 576,
            "Pss": 0,
            "Shared_Dirty": 0,
            "SwapPss": 0,
            "AnonHugePages": 0
          },
          {
            "category": "anonymous",
            "detail": "[anon:scudo:primary_reserve]",
            "mapping_count": 34,
            "Anonymous": 0,
            "Rss": 0,
            "Private_Clean": 0,
            "Shared_Clean": 0,
            "Referenced": 0,
            "Swap": 0,
            "Private_Dirty": 0,
            "Size": 8620800,
            "Pss": 0,
            "Shared_Dirty": 0,
            "SwapPss": 0,
            "AnonHugePages": 0
          },
          {
            "category": "special_mappings",
            "detail": "[page size compat]",
            "mapping_count": 6,
            "Anonymous": 0,
            "Rss": 0,
            "Private_Clean": 0,
            "Shared_Clean": 0,
            "Referenced": 0,
            "Swap": 0,
            "Private_Dirty": 0,
            "Size": 48,
            "Pss": 0,
            "Shared_Dirty": 0,
            "SwapPss": 0,
            "AnonHugePages": 0
          },
          {
            "category": "special_mappings",
            "detail": "[vvar]",
            "mapping_count": 1,
            "Anonymous": 0,
            "Rss": 0,
            "Private_Clean": 0,
            "Shared_Clean": 0,
            "Referenced": 0,
            "Swap": 0,
            "Private_Dirty": 0,
            "Size": 8,
            "Pss": 0,
            "Shared_Dirty": 0,
            "SwapPss": 0,
            "AnonHugePages": 0
          }
        ]
      }
    },
    "after": {
      "captured_utc": "2026-07-17T05:24:22.649567+00:00",
      "pid": 30577,
      "summary": {
        "status": {
          "Name": "liblfmserver.so",
          "Umask": "0077",
          "State": "S (sleeping)",
          "Tgid": "30577",
          "Ngid": "0",
          "Pid": "30577",
          "PPid": "30487",
          "TracerPid": "0",
          "Uid": "10538\t10538\t10538\t10538",
          "Gid": "10538\t10538\t10538\t10538",
          "FDSize": "256",
          "Groups": "3003 9997 20538 50538 99909997",
          "Kthread": "0",
          "VmPeak": 14084892,
          "VmSize": 13946388,
          "VmLck": 0,
          "VmPin": 0,
          "VmHWM": 1914780,
          "VmRSS": 1900196,
          "RssAnon": 1175872,
          "RssFile": 724024,
          "RssShmem": 300,
          "VmData": 2085096,
          "VmStk": 136,
          "VmExe": 1220,
          "VmLib": 9744,
          "VmPTE": 4120,
          "VmSwap": 0,
          "CoreDumping": "0",
          "THP_enabled": "1",
          "untag_mask": "0xffffffffffffff",
          "Threads": "17",
          "SigQ": "0/57649",
          "SigPnd": "0000000000000000",
          "ShdPnd": "0000000000000000",
          "SigBlk": "0000000080001204",
          "SigIgn": "0000002000001001",
          "SigCgt": "0000004c400084fa",
          "CapInh": "0000000000000000",
          "CapPrm": "0000000000000000",
          "CapEff": "0000000000000000",
          "CapBnd": "0000000000000000",
          "CapAmb": "0000000000000000",
          "NoNewPrivs": "0",
          "Seccomp": "2",
          "Seccomp_filters": "1",
          "Speculation_Store_Bypass": "thread vulnerable",
          "SpeculationIndirectBranch": "unknown",
          "Cpus_allowed": "ff",
          "Cpus_allowed_list": "0-7",
          "Mems_allowed": "1",
          "Mems_allowed_list": "0",
          "voluntary_ctxt_switches": "24",
          "nonvoluntary_ctxt_switches": "163"
        },
        "smaps_totals_kib": {
          "Anonymous": 1176248,
          "Rss": 1900796,
          "Private_Clean": 721548,
          "Shared_Clean": 2672,
          "Referenced": 1900744,
          "Swap": 0,
          "Private_Dirty": 1176248,
          "Size": 13946388,
          "Pss": 1897810,
          "Shared_Dirty": 328,
          "SwapPss": 0,
          "AnonHugePages": 387072
        },
        "category_totals_kib": {
          "anonymous": {
            "Anonymous": 1175908,
            "Rss": 1175908,
            "Private_Clean": 0,
            "Shared_Clean": 0,
            "Referenced": 1175908,
            "Swap": 0,
            "Private_Dirty": 1175908,
            "Size": 13217892,
            "Pss": 1175908,
            "Shared_Dirty": 0,
            "SwapPss": 0,
            "AnonHugePages": 387072
          },
          "gguf_weights": {
            "Anonymous": 0,
            "Rss": 714380,
            "Private_Clean": 714380,
            "Shared_Clean": 0,
            "Referenced": 714380,
            "Swap": 0,
            "Private_Dirty": 0,
            "Size": 714380,
            "Pss": 714380,
            "Shared_Dirty": 0,
            "SwapPss": 0,
            "AnonHugePages": 0
          },
          "shared_libraries": {
            "Anonymous": 296,
            "Rss": 9260,
            "Private_Clean": 7168,
            "Shared_Clean": 1796,
            "Referenced": 9208,
            "Swap": 0,
            "Private_Dirty": 296,
            "Size": 11000,
            "Pss": 7472,
            "Shared_Dirty": 0,
            "SwapPss": 0,
            "AnonHugePages": 0
          },
          "other_file_backed": {
            "Anonymous": 44,
            "Rss": 916,
            "Private_Clean": 0,
            "Shared_Clean": 872,
            "Referenced": 916,
            "Swap": 0,
            "Private_Dirty": 44,
            "Size": 1492,
            "Pss": 50,
            "Shared_Dirty": 0,
            "SwapPss": 0,
            "AnonHugePages": 0
          },
          "device_mappings": {
            "Anonymous": 0,
            "Rss": 328,
            "Private_Clean": 0,
            "Shared_Clean": 0,
            "Referenced": 328,
            "Swap": 0,
            "Private_Dirty": 0,
            "Size": 1560,
            "Pss": 0,
            "Shared_Dirty": 328,
            "SwapPss": 0,
            "AnonHugePages": 0
          },
          "special_mappings": {
            "Anonymous": 0,
            "Rss": 4,
            "Private_Clean": 0,
            "Shared_Clean": 4,
            "Referenced": 4,
            "Swap": 0,
            "Private_Dirty": 0,
            "Size": 64,
            "Pss": 0,
            "Shared_Dirty": 0,
            "SwapPss": 0,
            "AnonHugePages": 0
          }
        },
        "rows": [
          {
            "category": "anonymous",
            "detail": "[anon:scudo:secondary]",
            "mapping_count": 96,
            "Anonymous": 1150968,
            "Rss": 1150968,
            "Private_Clean": 0,
            "Shared_Clean": 0,
            "Referenced": 1150968,
            "Swap": 0,
            "Private_Dirty": 1150968,
            "Size": 2036632,
            "Pss": 1150968,
            "Shared_Dirty": 0,
            "SwapPss": 0,
            "AnonHugePages": 387072
          },
          {
            "category": "gguf_weights",
            "detail": "LFM2.5-Audio-1.5B-Q4_0.gguf",
            "mapping_count": 2,
            "Anonymous": 0,
            "Rss": 667908,
            "Private_Clean": 667908,
            "Shared_Clean": 0,
            "Referenced": 667908,
            "Swap": 0,
            "Private_Dirty": 0,
            "Size": 667908,
            "Pss": 667908,
            "Shared_Dirty": 0,
            "SwapPss": 0,
            "AnonHugePages": 0
          },
          {
            "category": "gguf_weights",
            "detail": "tokenizer-LFM2.5-Audio-1.5B-Q4_0.gguf",
            "mapping_count": 2,
            "Anonymous": 0,
            "Rss": 46472,
            "Private_Clean": 46472,
            "Shared_Clean": 0,
            "Referenced": 46472,
            "Swap": 0,
            "Private_Dirty": 0,
            "Size": 46472,
            "Pss": 46472,
            "Shared_Dirty": 0,
            "SwapPss": 0,
            "AnonHugePages": 0
          },
          {
            "category": "anonymous",
            "detail": "[anon:scudo:primary]",
            "mapping_count": 33,
            "Anonymous": 23672,
            "Rss": 23672,
            "Private_Clean": 0,
            "Shared_Clean": 0,
            "Referenced": 23672,
            "Swap": 0,
            "Private_Dirty": 23672,
            "Size": 29952,
            "Pss": 23672,
            "Shared_Dirty": 0,
            "SwapPss": 0,
            "AnonHugePages": 0
          },
          {
            "category": "shared_libraries",
            "detail": "libliquid-audio.so",
            "mapping_count": 3,
            "Anonymous": 48,
            "Rss": 1852,
            "Private_Clean": 1804,
            "Shared_Clean": 0,
            "Referenced": 1852,
            "Swap": 0,
            "Private_Dirty": 48,
            "Size": 2428,
            "Pss": 1852,
            "Shared_Dirty": 0,
            "SwapPss": 0,
            "AnonHugePages": 0
          },
          {
            "category": "shared_libraries",
            "detail": "libllama.so",
            "mapping_count": 3,
            "Anonymous": 48,
            "Rss": 1760,
            "Private_Clean": 1712,
            "Shared_Clean": 0,
            "Referenced": 1760,
            "Swap": 0,
            "Private_Dirty": 48,
            "Size": 2080,
            "Pss": 1760,
            "Shared_Dirty": 0,
            "SwapPss": 0,
            "AnonHugePages": 0
          },
          {
            "category": "shared_libraries",
            "detail": "liblfmserver.so",
            "mapping_count": 3,
            "Anonymous": 28,
            "Rss": 1056,
            "Private_Clean": 1028,
            "Shared_Clean": 0,
            "Referenced": 1056,
            "Swap": 0,
            "Private_Dirty": 28,
            "Size": 1248,
            "Pss": 1056,
            "Shared_Dirty": 0,
            "SwapPss": 0,
            "AnonHugePages": 0
          },
          {
            "category": "other_file_backed",
            "detail": "/apex/com.android.runtime/bin/linker64",
            "mapping_count": 4,
            "Anonymous": 44,
            "Rss": 916,
            "Private_Clean": 0,
            "Shared_Clean": 872,
            "Referenced": 916,
            "Swap": 0,
            "Private_Dirty": 44,
            "Size": 1492,
            "Pss": 50,
            "Shared_Dirty": 0,
            "SwapPss": 0,
            "AnonHugePages": 0
          },
          {
            "category": "shared_libraries",
            "detail": "libggml-base.so",
            "mapping_count": 3,
            "Anonymous": 36,
            "Rss": 868,
            "Private_Clean": 832,
            "Shared_Clean": 0,
            "Referenced": 868,
            "Swap": 0,
            "Private_Dirty": 36,
            "Size": 932,
            "Pss": 868,
            "Shared_Dirty": 0,
            "SwapPss": 0,
            "AnonHugePages": 0
          },
          {
            "category": "shared_libraries",
            "detail": "libc++.so",
            "mapping_count": 4,
            "Anonymous": 36,
            "Rss": 820,
            "Private_Clean": 0,
            "Shared_Clean": 784,
            "Referenced": 768,
            "Swap": 0,
            "Private_Dirty": 36,
            "Size": 1028,
            "Pss": 39,
            "Shared_Dirty": 0,
            "SwapPss": 0,
            "AnonHugePages": 0
          },
          {
            "category": "shared_libraries",
            "detail": "libc.so",
            "mapping_count": 4,
            "Anonymous": 20,
            "Rss": 784,
            "Private_Clean": 0,
            "Shared_Clean": 764,
            "Referenced": 784,
            "Swap": 0,
            "Private_Dirty": 20,
            "Size": 960,
            "Pss": 21,
            "Shared_Dirty": 0,
            "SwapPss": 0,
            "AnonHugePages": 0
          },
          {
            "category": "anonymous",
            "detail": "[anon:.bss]",
            "mapping_count": 16,
            "Anonymous": 712,
            "Rss": 712,
            "Private_Clean": 0,
            "Shared_Clean": 0,
            "Referenced": 712,
            "Swap": 0,
            "Private_Dirty": 712,
            "Size": 944,
            "Pss": 712,
            "Shared_Dirty": 0,
            "SwapPss": 0,
            "AnonHugePages": 0
          },
          {
            "category": "shared_libraries",
            "detail": "libggml.so",
            "mapping_count": 3,
            "Anonymous": 28,
            "Rss": 660,
            "Private_Clean": 632,
            "Shared_Clean": 0,
            "Referenced": 660,
            "Swap": 0,
            "Private_Dirty": 28,
            "Size": 660,
            "Pss": 660,
            "Shared_Dirty": 0,
            "SwapPss": 0,
            "AnonHugePages": 0
          },
          {
            "category": "shared_libraries",
            "detail": "libggml-cpu-android_armv8.6_1.so",
            "mapping_count": 3,
            "Anonymous": 16,
            "Rss": 636,
            "Private_Clean": 620,
            "Shared_Clean": 0,
            "Referenced": 636,
            "Swap": 0,
            "Private_Dirty": 16,
            "Size": 700,
            "Pss": 636,
            "Shared_Dirty": 0,
            "SwapPss": 0,
            "AnonHugePages": 0
          },
          {
            "category": "shared_libraries",
            "detail": "libmtmd.so",
            "mapping_count": 3,
            "Anonymous": 16,
            "Rss": 556,
            "Private_Clean": 540,
            "Shared_Clean": 0,
            "Referenced": 556,
            "Swap": 0,
            "Private_Dirty": 16,
            "Size": 684,
            "Pss": 556,
            "Shared_Dirty": 0,
            "SwapPss": 0,
            "AnonHugePages": 0
          },
          {
            "category": "device_mappings",
            "detail": "/dev/__properties__/property_info",
            "mapping_count": 2,
            "Anonymous": 0,
            "Rss": 268,
            "Private_Clean": 0,
            "Shared_Clean": 0,
            "Referenced": 268,
            "Swap": 0,
            "Private_Dirty": 0,
            "Size": 280,
            "Pss": 0,
            "Shared_Dirty": 268,
            "SwapPss": 0,
            "AnonHugePages": 0
          },
          {
            "category": "shared_libraries",
            "detail": "libm.so",
            "mapping_count": 4,
            "Anonymous": 8,
            "Rss": 216,
            "Private_Clean": 0,
            "Shared_Clean": 208,
            "Referenced": 216,
            "Swap": 0,
            "Private_Dirty": 8,
            "Size": 228,
            "Pss": 12,
            "Shared_Dirty": 0,
            "SwapPss": 0,
            "AnonHugePages": 0
          },
          {
            "category": "anonymous",
            "detail": "[anon:bionic_alloc_small_objects]",
            "mapping_count": 14,
            "Anonymous": 116,
            "Rss": 116,
            "Private_Clean": 0,
            "Shared_Clean": 0,
            "Referenced": 116,
            "Swap": 0,
            "Private_Dirty": 116,
            "Size": 116,
            "Pss": 116,
            "Shared_Dirty": 0,
            "SwapPss": 0,
            "AnonHugePages": 0
          },
          {
            "category": "anonymous",
            "detail": "[stack]",
            "mapping_count": 1,
            "Anonymous": 92,
            "Rss": 92,
            "Private_Clean": 0,
            "Shared_Clean": 0,
            "Referenced": 92,
            "Swap": 0,
            "Private_Dirty": 92,
            "Size": 136,
            "Pss": 92,
            "Shared_Dirty": 0,
            "SwapPss": 0,
            "AnonHugePages": 0
          },
          {
            "category": "anonymous",
            "detail": "[anon:System property context nodes]",
            "mapping_count": 2,
            "Anonymous": 48,
            "Rss": 48,
            "Private_Clean": 0,
            "Shared_Clean": 0,
            "Referenced": 48,
            "Swap": 0,
            "Private_Dirty": 48,
            "Size": 48,
            "Pss": 48,
            "Shared_Dirty": 0,
            "SwapPss": 0,
            "AnonHugePages": 0
          },
          {
            "category": "shared_libraries",
            "detail": "libnetd_client.so",
            "mapping_count": 4,
            "Anonymous": 8,
            "Rss": 40,
            "Private_Clean": 0,
            "Shared_Clean": 32,
            "Referenced": 40,
            "Swap": 0,
            "Private_Dirty": 8,
            "Size": 40,
            "Pss": 8,
            "Shared_Dirty": 0,
            "SwapPss": 0,
            "AnonHugePages": 0
          },
          {
            "category": "anonymous",
            "detail": "[anon:stack_and_tls:30641]",
            "mapping_count": 1,
            "Anonymous": 36,
            "Rss": 36,
            "Private_Clean": 0,
            "Shared_Clean": 0,
            "Referenced": 36,
            "Swap": 0,
            "Private_Dirty": 36,
            "Size": 1008,
            "Pss": 36,
            "Shared_Dirty": 0,
            "SwapPss": 0,
            "AnonHugePages": 0
          },
          {
            "category": "anonymous",
            "detail": "[anon:linker_alloc]",
            "mapping_count": 4,
            "Anonymous": 28,
            "Rss": 28,
            "Private_Clean": 0,
            "Shared_Clean": 0,
            "Referenced": 28,
            "Swap": 0,
            "Private_Dirty": 28,
            "Size": 1920,
            "Pss": 28,
            "Shared_Dirty": 0,
            "SwapPss": 0,
            "AnonHugePages": 0
          },
          {
            "category": "anonymous",
            "detail": "[anon:stack_and_tls:30637]",
            "mapping_count": 1,
            "Anonymous": 20,
            "Rss": 20,
            "Private_Clean": 0,
            "Shared_Clean": 0,
            "Referenced": 20,
            "Swap": 0,
            "Private_Dirty": 20,
            "Size": 1008,
            "Pss": 20,
            "Shared_Dirty": 0,
            "SwapPss": 0,
            "AnonHugePages": 0
          },
          {
            "category": "anonymous",
            "detail": "[anon:cfi shadow]",
            "mapping_count": 10,
            "Anonymous": 20,
            "Rss": 20,
            "Private_Clean": 0,
            "Shared_Clean": 0,
            "Referenced": 20,
            "Swap": 0,
            "Private_Dirty": 20,
            "Size": 2097152,
            "Pss": 20,
            "Shared_Dirty": 0,
            "SwapPss": 0,
            "AnonHugePages": 0
          },
          {
            "category": "device_mappings",
            "detail": "/dev/__properties__/u:object_r:build_prop:s0",
            "mapping_count": 1,
            "Anonymous": 0,
            "Rss": 16,
            "Private_Clean": 0,
            "Shared_Clean": 0,
            "Referenced": 16,
            "Swap": 0,
            "Private_Dirty": 0,
            "Size": 128,
            "Pss": 0,
            "Shared_Dirty": 16,
            "SwapPss": 0,
            "AnonHugePages": 0
          },
          {
            "category": "device_mappings",
            "detail": "/dev/__properties__/u:object_r:debug_prop:s0",
            "mapping_count": 2,
            "Anonymous": 0,
            "Rss": 16,
            "Private_Clean": 0,
            "Shared_Clean": 0,
            "Referenced": 16,
            "Swap": 0,
            "Private_Dirty": 0,
            "Size": 256,
            "Pss": 0,
            "Shared_Dirty": 16,
            "SwapPss": 0,
            "AnonHugePages": 0
          },
          {
            "category": "anonymous",
            "detail": "[anon:stack_and_tls:30644]",
            "mapping_count": 1,
            "Anonymous": 12,
            "Rss": 12,
            "Private_Clean": 0,
            "Shared_Clean": 0,
            "Referenced": 12,
            "Swap": 0,
            "Private_Dirty": 12,
            "Size": 1008,
            "Pss": 12,
            "Shared_Dirty": 0,
            "SwapPss": 0,
            "AnonHugePages": 0
          },
          {
            "category": "anonymous",
            "detail": "[anon:stack_and_tls:30643]",
            "mapping_count": 1,
            "Anonymous": 12,
            "Rss": 12,
            "Private_Clean": 0,
            "Shared_Clean": 0,
            "Referenced": 12,
            "Swap": 0,
            "Private_Dirty": 12,
            "Size": 1008,
            "Pss": 12,
            "Shared_Dirty": 0,
            "SwapPss": 0,
            "AnonHugePages": 0
          },
          {
            "category": "anonymous",
            "detail": "[anon:stack_and_tls:30642]",
            "mapping_count": 1,
            "Anonymous": 12,
            "Rss": 12,
            "Private_Clean": 0,
            "Shared_Clean": 0,
            "Referenced": 12,
            "Swap": 0,
            "Private_Dirty": 12,
            "Size": 1008,
            "Pss": 12,
            "Shared_Dirty": 0,
            "SwapPss": 0,
            "AnonHugePages": 0
          },
          {
            "category": "anonymous",
            "detail": "[anon:stack_and_tls:30640]",
            "mapping_count": 1,
            "Anonymous": 12,
            "Rss": 12,
            "Private_Clean": 0,
            "Shared_Clean": 0,
            "Referenced": 12,
            "Swap": 0,
            "Private_Dirty": 12,
            "Size": 1008,
            "Pss": 12,
            "Shared_Dirty": 0,
            "SwapPss": 0,
            "AnonHugePages": 0
          },
          {
            "category": "anonymous",
            "detail": "[anon:stack_and_tls:30639]",
            "mapping_count": 1,
            "Anonymous": 12,
            "Rss": 12,
            "Private_Clean": 0,
            "Shared_Clean": 0,
            "Referenced": 12,
            "Swap": 0,
            "Private_Dirty": 12,
            "Size": 1008,
            "Pss": 12,
            "Shared_Dirty": 0,
            "SwapPss": 0,
            "AnonHugePages": 0
          },
          {
            "category": "anonymous",
            "detail": "[anon:stack_and_tls:30638]",
            "mapping_count": 1,
            "Anonymous": 12,
            "Rss": 12,
            "Private_Clean": 0,
            "Shared_Clean": 0,
            "Referenced": 12,
            "Swap": 0,
            "Private_Dirty": 12,
            "Size": 1008,
            "Pss": 12,
            "Shared_Dirty": 0,
            "SwapPss": 0,
            "AnonHugePages": 0
          },
          {
            "category": "anonymous",
            "detail": "[anon:stack_and_tls:30636]",
            "mapping_count": 1,
            "Anonymous": 12,
            "Rss": 12,
            "Private_Clean": 0,
            "Shared_Clean": 0,
            "Referenced": 12,
            "Swap": 0,
            "Private_Dirty": 12,
            "Size": 1008,
            "Pss": 12,
            "Shared_Dirty": 0,
            "SwapPss": 0,
            "AnonHugePages": 0
          },
          {
            "category": "anonymous",
            "detail": "[anon:stack_and_tls:30635]",
            "mapping_count": 1,
            "Anonymous": 12,
            "Rss": 12,
            "Private_Clean": 0,
            "Shared_Clean": 0,
            "Referenced": 12,
            "Swap": 0,
            "Private_Dirty": 12,
            "Size": 1008,
            "Pss": 12,
            "Shared_Dirty": 0,
            "SwapPss": 0,
            "AnonHugePages": 0
          },
          {
            "category": "anonymous",
            "detail": "[anon:stack_and_tls:30634]",
            "mapping_count": 1,
            "Anonymous": 12,
            "Rss": 12,
            "Private_Clean": 0,
            "Shared_Clean": 0,
            "Referenced": 12,
            "Swap": 0,
            "Private_Dirty": 12,
            "Size": 1008,
            "Pss": 12,
            "Shared_Dirty": 0,
            "SwapPss": 0,
            "AnonHugePages": 0
          },
          {
            "category": "anonymous",
            "detail": "[anon:stack_and_tls:30633]",
            "mapping_count": 1,
            "Anonymous": 12,
            "Rss": 12,
            "Private_Clean": 0,
            "Shared_Clean": 0,
            "Referenced": 12,
            "Swap": 0,
            "Private_Dirty": 12,
            "Size": 1008,
            "Pss": 12,
            "Shared_Dirty": 0,
            "SwapPss": 0,
            "AnonHugePages": 0
          },
          {
            "category": "anonymous",
            "detail": "[anon:stack_and_tls:30632]",
            "mapping_count": 1,
            "Anonymous": 12,
            "Rss": 12,
            "Private_Clean": 0,
            "Shared_Clean": 0,
            "Referenced": 12,
            "Swap": 0,
            "Private_Dirty": 12,
            "Size": 1008,
            "Pss": 12,
            "Shared_Dirty": 0,
            "SwapPss": 0,
            "AnonHugePages": 0
          },
          {
            "category": "anonymous",
            "detail": "[anon:stack_and_tls:30631]",
            "mapping_count": 1,
            "Anonymous": 12,
            "Rss": 12,
            "Private_Clean": 0,
            "Shared_Clean": 0,
            "Referenced": 12,
            "Swap": 0,
            "Private_Dirty": 12,
            "Size": 1008,
            "Pss": 12,
            "Shared_Dirty": 0,
            "SwapPss": 0,
            "AnonHugePages": 0
          },
          {
            "category": "anonymous",
            "detail": "[anon:stack_and_tls:30630]",
            "mapping_count": 1,
            "Anonymous": 12,
            "Rss": 12,
            "Private_Clean": 0,
            "Shared_Clean": 0,
            "Referenced": 12,
            "Swap": 0,
            "Private_Dirty": 12,
            "Size": 1008,
            "Pss": 12,
            "Shared_Dirty": 0,
            "SwapPss": 0,
            "AnonHugePages": 0
          },
          {
            "category": "anonymous",
            "detail": "[anon:stack_and_tls:30587]",
            "mapping_count": 1,
            "Anonymous": 12,
            "Rss": 12,
            "Private_Clean": 0,
            "Shared_Clean": 0,
            "Referenced": 12,
            "Swap": 0,
            "Private_Dirty": 12,
            "Size": 1008,
            "Pss": 12,
            "Shared_Dirty": 0,
            "SwapPss": 0,
            "AnonHugePages": 0
          },
          {
            "category": "shared_libraries",
            "detail": "libdl.so",
            "mapping_count": 3,
            "Anonymous": 4,
            "Rss": 12,
            "Private_Clean": 0,
            "Shared_Clean": 8,
            "Referenced": 12,
            "Swap": 0,
            "Private_Dirty": 4,
            "Size": 12,
            "Pss": 4,
            "Shared_Dirty": 0,
            "SwapPss": 0,
            "AnonHugePages": 0
          },
          {
            "category": "anonymous",
            "detail": "[anon:stack_and_tls:main]",
            "mapping_count": 1,
            "Anonymous": 12,
            "Rss": 12,
            "Private_Clean": 0,
            "Shared_Clean": 0,
            "Referenced": 12,
            "Swap": 0,
            "Private_Dirty": 12,
            "Size": 16,
            "Pss": 12,
            "Shared_Dirty": 0,
            "SwapPss": 0,
            "AnonHugePages": 0
          },
          {
            "category": "device_mappings",
            "detail": "/dev/__properties__/properties_serial",
            "mapping_count": 2,
            "Anonymous": 0,
            "Rss": 8,
            "Private_Clean": 0,
            "Shared_Clean": 0,
            "Referenced": 8,
            "Swap": 0,
            "Private_Dirty": 0,
            "Size": 256,
            "Pss": 0,
            "Shared_Dirty": 8,
            "SwapPss": 0,
            "AnonHugePages": 0
          },
          {
            "category": "anonymous",
            "detail": "[anon:atexit handlers]",
            "mapping_count": 2,
            "Anonymous": 8,
            "Rss": 8,
            "Private_Clean": 0,
            "Shared_Clean": 0,
            "Referenced": 8,
            "Swap": 0,
            "Private_Dirty": 8,
            "Size": 8,
            "Pss": 8,
            "Shared_Dirty": 0,
            "SwapPss": 0,
            "AnonHugePages": 0
          },
          {
            "category": "anonymous",
            "detail": "[anon:arc4random data]",
            "mapping_count": 2,
            "Anonymous": 8,
            "Rss": 8,
            "Private_Clean": 0,
            "Shared_Clean": 0,
            "Referenced": 8,
            "Swap": 0,
            "Private_Dirty": 8,
            "Size": 8,
            "Pss": 8,
            "Shared_Dirty": 0,
            "SwapPss": 0,
            "AnonHugePages": 0
          },
          {
            "category": "device_mappings",
            "detail": "/dev/__properties__/u:object_r:heapprofd_prop:s0",
            "mapping_count": 1,
            "Anonymous": 0,
            "Rss": 4,
            "Private_Clean": 0,
            "Shared_Clean": 0,
            "Referenced": 4,
            "Swap": 0,
            "Private_Dirty": 0,
            "Size": 128,
            "Pss": 0,
            "Shared_Dirty": 4,
            "SwapPss": 0,
            "AnonHugePages": 0
          },
          {
            "category": "device_mappings",
            "detail": "/dev/__properties__/u:object_r:libc_debug_prop:s0",
            "mapping_count": 1,
            "Anonymous": 0,
            "Rss": 4,
            "Private_Clean": 0,
            "Shared_Clean": 0,
            "Referenced": 4,
            "Swap": 0,
            "Private_Dirty": 0,
            "Size": 128,
            "Pss": 0,
            "Shared_Dirty": 4,
            "SwapPss": 0,
            "AnonHugePages": 0
          },
          {
            "category": "device_mappings",
            "detail": "/dev/__properties__/u:object_r:gwp_asan_prop:s0",
            "mapping_count": 1,
            "Anonymous": 0,
            "Rss": 4,
            "Private_Clean": 0,
            "Shared_Clean": 0,
            "Referenced": 4,
            "Swap": 0,
            "Private_Dirty": 0,
            "Size": 128,
            "Pss": 0,
            "Shared_Dirty": 4,
            "SwapPss": 0,
            "AnonHugePages": 0
          },
          {
            "category": "device_mappings",
            "detail": "/dev/__properties__/u:object_r:vendor_socket_hook_prop:s0",
            "mapping_count": 1,
            "Anonymous": 0,
            "Rss": 4,
            "Private_Clean": 0,
            "Shared_Clean": 0,
            "Referenced": 4,
            "Swap": 0,
            "Private_Dirty": 0,
            "Size": 128,
            "Pss": 0,
            "Shared_Dirty": 4,
            "SwapPss": 0,
            "AnonHugePages": 0
          },
          {
            "category": "device_mappings",
            "detail": "/dev/__properties__/u:object_r:vndk_prop:s0",
            "mapping_count": 1,
            "Anonymous": 0,
            "Rss": 4,
            "Private_Clean": 0,
            "Shared_Clean": 0,
            "Referenced": 4,
            "Swap": 0,
            "Private_Dirty": 0,
            "Size": 128,
            "Pss": 0,
            "Shared_Dirty": 4,
            "SwapPss": 0,
            "AnonHugePages": 0
          },
          {
            "category": "special_mappings",
            "detail": "[vdso]",
            "mapping_count": 1,
            "Anonymous": 0,
            "Rss": 4,
            "Private_Clean": 0,
            "Shared_Clean": 4,
            "Referenced": 4,
            "Swap": 0,
            "Private_Dirty": 0,
            "Size": 8,
            "Pss": 0,
            "Shared_Dirty": 0,
            "SwapPss": 0,
            "AnonHugePages": 0
          },
          {
            "category": "anonymous",
            "detail": "<anonymous>",
            "mapping_count": 226,
            "Anonymous": 0,
            "Rss": 0,
            "Private_Clean": 0,
            "Shared_Clean": 0,
            "Referenced": 0,
            "Swap": 0,
            "Private_Dirty": 0,
            "Size": 413488,
            "Pss": 0,
            "Shared_Dirty": 0,
            "SwapPss": 0,
            "AnonHugePages": 0
          },
          {
            "category": "anonymous",
            "detail": "[anon:thread signal stack]",
            "mapping_count": 17,
            "Anonymous": 0,
            "Rss": 0,
            "Private_Clean": 0,
            "Shared_Clean": 0,
            "Referenced": 0,
            "Swap": 0,
            "Private_Dirty": 0,
            "Size": 544,
            "Pss": 0,
            "Shared_Dirty": 0,
            "SwapPss": 0,
            "AnonHugePages": 0
          },
          {
            "category": "anonymous",
            "detail": "[anon:scudo:primary_reserve]",
            "mapping_count": 34,
            "Anonymous": 0,
            "Rss": 0,
            "Private_Clean": 0,
            "Shared_Clean": 0,
            "Referenced": 0,
            "Swap": 0,
            "Private_Dirty": 0,
            "Size": 8620800,
            "Pss": 0,
            "Shared_Dirty": 0,
            "SwapPss": 0,
            "AnonHugePages": 0
          },
          {
            "category": "special_mappings",
            "detail": "[page size compat]",
            "mapping_count": 6,
            "Anonymous": 0,
            "Rss": 0,
            "Private_Clean": 0,
            "Shared_Clean": 0,
            "Referenced": 0,
            "Swap": 0,
            "Private_Dirty": 0,
            "Size": 48,
            "Pss": 0,
            "Shared_Dirty": 0,
            "SwapPss": 0,
            "AnonHugePages": 0
          },
          {
            "category": "special_mappings",
            "detail": "[vvar]",
            "mapping_count": 1,
            "Anonymous": 0,
            "Rss": 0,
            "Private_Clean": 0,
            "Shared_Clean": 0,
            "Referenced": 0,
            "Swap": 0,
            "Private_Dirty": 0,
            "Size": 8,
            "Pss": 0,
            "Shared_Dirty": 0,
            "SwapPss": 0,
            "AnonHugePages": 0
          }
        ]
      }
    }
  }
}
